pydantic_aiohttp/__init__.py
pydantic_aiohttp/client.py
pydantic_aiohttp/encoders.py
pydantic_aiohttp/errors.py
pydantic_aiohttp/responses.py
pydantic_aiohttp/types.py
pydantic_aiohttp/utils.py
pydantic_aiohttp-1.1.0.dist-info/METADATA
pydantic_aiohttp-1.1.0.dist-info/WHEEL
pydantic_aiohttp-1.1.0.dist-info/licenses/LICENSE
pydantic_aiohttp-1.1.0.dist-info/RECORD
