Metadata-Version: 2.3
Name: pydantic_aiohttp
Version: 1.1.0
Summary: Simple HTTP Client based on aiohttp with integration of pydantic
Project-URL: Source, https://github.com/pylakey/pydantic_aiohttp
Project-URL: Homepage, https://github.com/pylakey/pydantic_aiohttp
Author-email: pylakey <pylakey@protonmail.com>
License: MIT License
License-File: LICENSE
Classifier: Framework :: AsyncIO
Classifier: License :: OSI Approved :: MIT License
Classifier: Operating System :: OS Independent
Classifier: Topic :: Software Development :: Libraries :: Python Modules
Classifier: Typing :: Typed
Requires-Python: >=3.9
Requires-Dist: aiofiles>=23.0.0
Requires-Dist: aiohttp[speedups]==3.*
Requires-Dist: pydantic<3,>=2
Requires-Dist: ujson>=5.7.0
Provides-Extra: dev
Requires-Dist: pytest<8.0,>=7.2; extra == 'dev'
